[
  {
    "subtype": "Dagger",
    "name": "匕首",
    "dice_count": 1,
    "dice_sides": 4,
    "base_ap_cost": 2,
    "hit_bonus": 0,
    "pen_bonus": 0,
    "range": 1,
    "reload_ap": 0,
    "damage_type": "Slash",
    "weight": "Light"
  },
  {
    "subtype": "Seax",
    "name": "萨克斯短刀",
    "dice_count": 1,
    "dice_sides": 6,
    "base_ap_cost": 3,
    "hit_bonus": 0,
    "pen_bonus": 0,
    "range": 1,
    "reload_ap": 0,
    "damage_type": "Slash",
    "weight": "Light"
  },
  {
    "subtype": "Kukri",
    "name": "廓尔喀刀",
    "dice_count": 1,
    "dice_sides": 4,
    "base_ap_cost": 2,
    "hit_bonus": 1,
    "pen_bonus": 0,
    "range": 1,
    "reload_ap": 0,
    "damage_type": "Slash",
    "weight": "Light"
  },
  {
    "subtype": "ArmingSword",
    "name": "武装剑",
    "dice_count": 1,
    "dice_sides": 10,
    "base_ap_cost": 4,
    "hit_bonus": 0,
    "pen_bonus": 1,
    "range": 1,
    "reload_ap": 0,
    "damage_type": "Slash",
    "weight": "Medium"
  },
  {
    "subtype": "BattleAxe",
    "name": "战斧",
    "dice_count": 1,
    "dice_sides": 12,
    "base_ap_cost": 4,
    "hit_bonus": 0,
    "pen_bonus": 1,
    "range": 1,
    "reload_ap": 0,
    "damage_type": "Slash",
    "weight": "Medium"
  },
  {
    "subtype": "NomadSaber",
    "name": "游牧弯刀",
    "dice_count": 1,
    "dice_sides": 8,
    "base_ap_cost": 4,
    "hit_bonus": 1,
    "pen_bonus": 1,
    "range": 1,
    "reload_ap": 0,
    "damage_type": "Slash",
    "weight": "Medium"
  },
  {
    "subtype": "Greatsword",
    "name": "巨剑",
    "dice_count": 3,
    "dice_sides": 6,
    "base_ap_cost": 6,
    "hit_bonus": 0,
    "pen_bonus": 2,
    "range": 1,
    "reload_ap": 0,
    "damage_type": "Slash",
    "weight": "Heavy"
  },
  {
    "subtype": "GreatAxe",
    "name": "巨斧",
    "dice_count": 2,
    "dice_sides": 10,
    "base_ap_cost": 6,
    "hit_bonus": 0,
    "pen_bonus": 2,
    "range": 1,
    "reload_ap": 0,
    "damage_type": "Slash",
    "weight": "Heavy"
  },
  {
    "subtype": "Glaive",
    "name": "偃月刀",
    "dice_count": 2,
    "dice_sides": 8,
    "base_ap_cost": 6,
    "hit_bonus": 1,
    "pen_bonus": 2,
    "range": 2,
    "reload_ap": 0,
    "damage_type": "Slash",
    "weight": "Heavy"
  },
  {
    "subtype": "Stiletto",
    "name": "锥刺",
    "dice_count": 1,
    "dice_sides": 4,
    "base_ap_cost": 2,
    "hit_bonus": 0,
    "pen_bonus": 1,
    "range": 1,
    "reload_ap": 0,
    "damage_type": "Pierce",
    "weight": "Light"
  },
  {
    "subtype": "SpikedDagger",
    "name": "穿甲短剑",
    "dice_count": 1,
    "dice_sides": 6,
    "base_ap_cost": 2,
    "hit_bonus": 0,
    "pen_bonus": 2,
    "range": 1,
    "reload_ap": 0,
    "damage_type": "Pierce",
    "weight": "Light"
  },
  {
    "subtype": "Rapier",
    "name": "刺剑",
    "dice_count": 1,
    "dice_sides": 8,
    "base_ap_cost": 3,
    "hit_bonus": 1,
    "pen_bonus": 2,
    "range": 1,
    "reload_ap": 0,
    "damage_type": "Pierce",
    "weight": "Light"
  },
  {
    "subtype": "InfantrySpear",
    "name": "步兵长矛",
    "dice_count": 1,
    "dice_sides": 10,
    "base_ap_cost": 4,
    "hit_bonus": 0,
    "pen_bonus": 3,
    "range": 2,
    "reload_ap": 0,
    "damage_type": "Pierce",
    "weight": "Medium"
  },
  {
    "subtype": "BroadSpear",
    "name": "阔头矛",
    "dice_count": 1,
    "dice_sides": 12,
    "base_ap_cost": 5,
    "hit_bonus": 0,
    "pen_bonus": 3,
    "range": 1,
    "reload_ap": 0,
    "damage_type": "Pierce",
    "weight": "Medium"
  },
  {
    "subtype": "Awlpike",
    "name": "锥头矛",
    "dice_count": 1,
    "dice_sides": 8,
    "base_ap_cost": 4,
    "hit_bonus": 1,
    "pen_bonus": 3,
    "range": 3,
    "reload_ap": 0,
    "damage_type": "Pierce",
    "weight": "Medium"
  },
  {
    "subtype": "Lance",
    "name": "骑士长枪",
    "dice_count": 2,
    "dice_sides": 10,
    "base_ap_cost": 6,
    "hit_bonus": 0,
    "pen_bonus": 4,
    "range": 2,
    "reload_ap": 0,
    "damage_type": "Pierce",
    "weight": "Heavy"
  },
  {
    "subtype": "Voulge",
    "name": "长柄斧",
    "dice_count": 2,
    "dice_sides": 8,
    "base_ap_cost": 6,
    "hit_bonus": 0,
    "pen_bonus": 4,
    "range": 2,
    "reload_ap": 0,
    "damage_type": "Pierce",
    "weight": "Heavy"
  },
  {
    "subtype": "Trident",
    "name": "三叉戟",
    "dice_count": 2,
    "dice_sides": 6,
    "base_ap_cost": 6,
    "hit_bonus": 1,
    "pen_bonus": 4,
    "range": 2,
    "reload_ap": 0,
    "damage_type": "Pierce",
    "weight": "Heavy"
  },
  {
    "subtype": "Club",
    "name": "木棒",
    "dice_count": 1,
    "dice_sides": 6,
    "base_ap_cost": 3,
    "hit_bonus": 0,
    "pen_bonus": 1,
    "range": 1,
    "reload_ap": 0,
    "damage_type": "Crush",
    "weight": "Light"
  },
  {
    "subtype": "LightHammer",
    "name": "轻战锤",
    "dice_count": 1,
    "dice_sides": 8,
    "base_ap_cost": 3,
    "hit_bonus": 0,
    "pen_bonus": 1,
    "range": 1,
    "reload_ap": 0,
    "damage_type": "Crush",
    "weight": "Light"
  },
  {
    "subtype": "Cestus",
    "name": "铁手套",
    "dice_count": 1,
    "dice_sides": 4,
    "base_ap_cost": 2,
    "hit_bonus": 1,
    "pen_bonus": 1,
    "range": 1,
    "reload_ap": 0,
    "damage_type": "Crush",
    "weight": "Light"
  },
  {
    "subtype": "WingedMace",
    "name": "翼形锤矛",
    "dice_count": 1,
    "dice_sides": 12,
    "base_ap_cost": 4,
    "hit_bonus": 0,
    "pen_bonus": 2,
    "range": 1,
    "reload_ap": 0,
    "damage_type": "Crush",
    "weight": "Medium"
  },
  {
    "subtype": "MilitaryHammer",
    "name": "军用锤",
    "dice_count": 2,
    "dice_sides": 8,
    "base_ap_cost": 5,
    "hit_bonus": 0,
    "pen_bonus": 2,
    "range": 1,
    "reload_ap": 0,
    "damage_type": "Crush",
    "weight": "Medium"
  },
  {
    "subtype": "Flail",
    "name": "连枷",
    "dice_count": 1,
    "dice_sides": 10,
    "base_ap_cost": 4,
    "hit_bonus": 1,
    "pen_bonus": 2,
    "range": 1,
    "reload_ap": 0,
    "damage_type": "Crush",
    "weight": "Medium"
  },
  {
    "subtype": "Maul",
    "name": "大锤",
    "dice_count": 3,
    "dice_sides": 8,
    "base_ap_cost": 7,
    "hit_bonus": 0,
    "pen_bonus": 3,
    "range": 1,
    "reload_ap": 0,
    "damage_type": "Crush",
    "weight": "Heavy"
  },
  {
    "subtype": "Greatclub",
    "name": "巨型木棒",
    "dice_count": 2,
    "dice_sides": 12,
    "base_ap_cost": 7,
    "hit_bonus": 0,
    "pen_bonus": 3,
    "range": 1,
    "reload_ap": 0,
    "damage_type": "Crush",
    "weight": "Heavy"
  },
  {
    "subtype": "Polehammer",
    "name": "长柄战锤",
    "dice_count": 2,
    "dice_sides": 10,
    "base_ap_cost": 7,
    "hit_bonus": 1,
    "pen_bonus": 3,
    "range": 2,
    "reload_ap": 0,
    "damage_type": "Crush",
    "weight": "Heavy"
  },
  {
    "subtype": "ThrowingKnife",
    "name": "飞刀",
    "dice_count": 1,
    "dice_sides": 4,
    "base_ap_cost": 2,
    "hit_bonus": 0,
    "pen_bonus": 0,
    "range": 4,
    "reload_ap": 0,
    "damage_type": "Slash",
    "weight": "Light"
  },
  {
    "subtype": "Dart",
    "name": "飞镖",
    "dice_count": 1,
    "dice_sides": 4,
    "base_ap_cost": 2,
    "hit_bonus": 0,
    "pen_bonus": 2,
    "range": 5,
    "reload_ap": 0,
    "damage_type": "Pierce",
    "weight": "Light"
  },
  {
    "subtype": "Francisca",
    "name": "弗兰西斯卡飞斧",
    "dice_count": 1,
    "dice_sides": 6,
    "base_ap_cost": 3,
    "hit_bonus": 1,
    "pen_bonus": 1,
    "range": 3,
    "reload_ap": 0,
    "damage_type": "Slash",
    "weight": "Light"
  },
  {
    "subtype": "Javelin",
    "name": "标枪",
    "dice_count": 1,
    "dice_sides": 8,
    "base_ap_cost": 4,
    "hit_bonus": 0,
    "pen_bonus": 3,
    "range": 6,
    "reload_ap": 0,
    "damage_type": "Pierce",
    "weight": "Medium"
  },
  {
    "subtype": "Pilum",
    "name": "重标枪",
    "dice_count": 1,
    "dice_sides": 10,
    "base_ap_cost": 5,
    "hit_bonus": 0,
    "pen_bonus": 4,
    "range": 5,
    "reload_ap": 0,
    "damage_type": "Pierce",
    "weight": "Medium"
  },
  {
    "subtype": "Harpoon",
    "name": "渔叉",
    "dice_count": 1,
    "dice_sides": 4,
    "base_ap_cost": 4,
    "hit_bonus": 1,
    "pen_bonus": 3,
    "range": 4,
    "reload_ap": 0,
    "damage_type": "Pierce",
    "weight": "Medium"
  },
  {
    "subtype": "StoneThrow",
    "name": "投石",
    "dice_count": 1,
    "dice_sides": 4,
    "base_ap_cost": 5,
    "hit_bonus": 0,
    "pen_bonus": 1,
    "range": 6,
    "reload_ap": 0,
    "damage_type": "Crush",
    "weight": "Heavy"
  },
  {
    "subtype": "HeavyJavelin",
    "name": "重标枪",
    "dice_count": 1,
    "dice_sides": 12,
    "base_ap_cost": 6,
    "hit_bonus": 0,
    "pen_bonus": 4,
    "range": 4,
    "reload_ap": 0,
    "damage_type": "Pierce",
    "weight": "Heavy"
  },
  {
    "subtype": "ThrowingHammer",
    "name": "投掷飞锤",
    "dice_count": 1,
    "dice_sides": 8,
    "base_ap_cost": 5,
    "hit_bonus": 1,
    "pen_bonus": 2,
    "range": 3,
    "reload_ap": 0,
    "damage_type": "Crush",
    "weight": "Heavy"
  },
  {
    "subtype": "Shortbow",
    "name": "短弓",
    "dice_count": 1,
    "dice_sides": 6,
    "base_ap_cost": 4,
    "hit_bonus": 0,
    "pen_bonus": 1,
    "range": 8,
    "reload_ap": 0,
    "damage_type": "Pierce",
    "weight": "Light"
  },
  {
    "subtype": "HuntingBow",
    "name": "狩猎弓",
    "dice_count": 1,
    "dice_sides": 8,
    "base_ap_cost": 5,
    "hit_bonus": 0,
    "pen_bonus": 1,
    "range": 10,
    "reload_ap": 0,
    "damage_type": "Pierce",
    "weight": "Light"
  },
  {
    "subtype": "NomadBow",
    "name": "游牧弓",
    "dice_count": 1,
    "dice_sides": 4,
    "base_ap_cost": 4,
    "hit_bonus": 1,
    "pen_bonus": 1,
    "range": 7,
    "reload_ap": 0,
    "damage_type": "Pierce",
    "weight": "Light"
  },
  {
    "subtype": "Strongbow",
    "name": "强弓",
    "dice_count": 1,
    "dice_sides": 8,
    "base_ap_cost": 5,
    "hit_bonus": 0,
    "pen_bonus": 2,
    "range": 10,
    "reload_ap": 0,
    "damage_type": "Pierce",
    "weight": "Medium"
  },
  {
    "subtype": "RecurveBow",
    "name": "反曲弓",
    "dice_count": 1,
    "dice_sides": 10,
    "base_ap_cost": 6,
    "hit_bonus": 0,
    "pen_bonus": 2,
    "range": 12,
    "reload_ap": 0,
    "damage_type": "Pierce",
    "weight": "Medium"
  },
  {
    "subtype": "WarBow",
    "name": "战弓",
    "dice_count": 1,
    "dice_sides": 8,
    "base_ap_cost": 5,
    "hit_bonus": 1,
    "pen_bonus": 2,
    "range": 11,
    "reload_ap": 0,
    "damage_type": "Pierce",
    "weight": "Medium"
  },
  {
    "subtype": "Longbow",
    "name": "长弓",
    "dice_count": 1,
    "dice_sides": 10,
    "base_ap_cost": 7,
    "hit_bonus": 0,
    "pen_bonus": 3,
    "range": 15,
    "reload_ap": 0,
    "damage_type": "Pierce",
    "weight": "Heavy"
  },
  {
    "subtype": "CompositeLongbow",
    "name": "复合长弓",
    "dice_count": 2,
    "dice_sides": 6,
    "base_ap_cost": 8,
    "hit_bonus": 0,
    "pen_bonus": 3,
    "range": 14,
    "reload_ap": 0,
    "damage_type": "Pierce",
    "weight": "Heavy"
  },
  {
    "subtype": "Greatbow",
    "name": "巨弓",
    "dice_count": 1,
    "dice_sides": 10,
    "base_ap_cost": 7,
    "hit_bonus": 1,
    "pen_bonus": 3,
    "range": 13,
    "reload_ap": 0,
    "damage_type": "Pierce",
    "weight": "Heavy"
  },
  {
    "subtype": "PistolCrossbow",
    "name": "手弩",
    "dice_count": 1,
    "dice_sides": 4,
    "base_ap_cost": 5,
    "hit_bonus": 1,
    "pen_bonus": 2,
    "range": 6,
    "reload_ap": 2,
    "damage_type": "Pierce",
    "weight": "Light"
  },
  {
    "subtype": "LightCrossbow",
    "name": "轻弩",
    "dice_count": 1,
    "dice_sides": 8,
    "base_ap_cost": 5,
    "hit_bonus": 0,
    "pen_bonus": 3,
    "range": 10,
    "reload_ap": 4,
    "damage_type": "Pierce",
    "weight": "Light"
  },
  {
    "subtype": "HuntingCrossbow",
    "name": "猎弩",
    "dice_count": 1,
    "dice_sides": 10,
    "base_ap_cost": 5,
    "hit_bonus": 0,
    "pen_bonus": 3,
    "range": 12,
    "reload_ap": 3,
    "damage_type": "Pierce",
    "weight": "Light"
  },
  {
    "subtype": "StandardCrossbow",
    "name": "标准弩",
    "dice_count": 1,
    "dice_sides": 10,
    "base_ap_cost": 6,
    "hit_bonus": 0,
    "pen_bonus": 3,
    "range": 12,
    "reload_ap": 5,
    "damage_type": "Pierce",
    "weight": "Medium"
  },
  {
    "subtype": "StrongCrossbow",
    "name": "强弩",
    "dice_count": 1,
    "dice_sides": 12,
    "base_ap_cost": 7,
    "hit_bonus": 0,
    "pen_bonus": 4,
    "range": 11,
    "reload_ap": 6,
    "damage_type": "Pierce",
    "weight": "Medium"
  },
  {
    "subtype": "SniperCrossbow",
    "name": "狙击弩",
    "dice_count": 1,
    "dice_sides": 8,
    "base_ap_cost": 6,
    "hit_bonus": 1,
    "pen_bonus": 4,
    "range": 16,
    "reload_ap": 7,
    "damage_type": "Pierce",
    "weight": "Medium"
  },
  {
    "subtype": "HeavyCrossbow",
    "name": "重弩",
    "dice_count": 2,
    "dice_sides": 6,
    "base_ap_cost": 8,
    "hit_bonus": 0,
    "pen_bonus": 4,
    "range": 14,
    "reload_ap": 8,
    "damage_type": "Pierce",
    "weight": "Heavy"
  },
  {
    "subtype": "SiegeCrossbow",
    "name": "攻城弩",
    "dice_count": 2,
    "dice_sides": 8,
    "base_ap_cost": 9,
    "hit_bonus": 0,
    "pen_bonus": 5,
    "range": 13,
    "reload_ap": 10,
    "damage_type": "Pierce",
    "weight": "Heavy"
  },
  {
    "subtype": "Ballista",
    "name": "床弩",
    "dice_count": 1,
    "dice_sides": 12,
    "base_ap_cost": 8,
    "hit_bonus": 1,
    "pen_bonus": 5,
    "range": 18,
    "reload_ap": 12,
    "damage_type": "Pierce",
    "weight": "Heavy"
  },
  {
    "subtype": "Unarmed",
    "name": "赤手空拳",
    "dice_count": 1,
    "dice_sides": 3,
    "base_ap_cost": 2,
    "hit_bonus": 0,
    "pen_bonus": 0,
    "range": 1,
    "reload_ap": 0,
    "damage_type": "Crush",
    "weight": "Light"
  },
  {
    "subtype": "Wand",
    "name": "魔杖",
    "dice_count": 1,
    "dice_sides": 4,
    "base_ap_cost": 2,
    "hit_bonus": 0,
    "pen_bonus": 0,
    "range": 1,
    "reload_ap": 0,
    "damage_type": "Crush",
    "weight": "Light"
  },
  {
    "subtype": "Orb",
    "name": "法球",
    "dice_count": 1,
    "dice_sides": 4,
    "base_ap_cost": 2,
    "hit_bonus": 0,
    "pen_bonus": 0,
    "range": 1,
    "reload_ap": 0,
    "damage_type": "Crush",
    "weight": "Light"
  },
  {
    "subtype": "Staff",
    "name": "法杖",
    "dice_count": 1,
    "dice_sides": 6,
    "base_ap_cost": 4,
    "hit_bonus": 1,
    "pen_bonus": 1,
    "range": 2,
    "reload_ap": 0,
    "damage_type": "Crush",
    "weight": "Light"
  }
]